runai/__init__.py
runai/elastic/__init__.py
runai/elastic/keras/__init__.py
runai/elastic/keras/models.py
runai/elastic/torch/__init__.py
runai/ga/__init__.py
runai/ga/keras/__init__.py
runai/ga/keras/hooks.py
runai/ga/keras/optimizers.py
runai/ga/torch/__init__.py
runai/ga/torch/optim.py
runai/hpo/__init__.py
runai/mp/__init__.py
runai/mp/keras/__init__.py
runai/mp/keras/layers/__init__.py
runai/mp/keras/layers/convolutional.py
runai/mp/keras/layers/coordinator.py
runai/mp/keras/layers/core.py
runai/mp/keras/layers/keep.py
runai/mp/keras/layers/merge.py
runai/mp/keras/layers/normalization.py
runai/mp/keras/layers/parallelised.py
runai/mp/keras/layers/pooling.py
runai/profiler/__init__.py
runai/profiler/profiler.py
runai/profiler/keras/__init__.py
runai/profiler/keras/hooks/__init__.py
runai/profiler/keras/hooks/make_callable.py
runai/profiler/keras/hooks/run_callable.py
runai/profiler/tf/__init__.py
runai/profiler/tf/hooks/__init__.py
runai/profiler/tf/hooks/session_run.py
runai/reporter/__init__.py
runai/reporter/report_promethues.py
runai/reporter/keras/__init__.py
runai/reporter/keras/keras_metric_reporter.py
runai/utils/__init__.py
runai/utils/attribute.py
runai/utils/flock.py
runai/utils/gpus.py
runai/utils/hook.py
runai/utils/log.py
runai/utils/random.py
runai-0.4.1.dist-info/LICENSE
runai-0.4.1.dist-info/METADATA
runai-0.4.1.dist-info/WHEEL
runai-0.4.1.dist-info/top_level.txt
runai-0.4.1.dist-info/RECORD
