Metadata-Version: 2.1
Name: runai
Version: 0.4.1
Summary: Run:AI Python library
Home-page: https://github.com/run-ai/runai
Author: Run:AI
Author-email: pypi@run.ai
License: UNKNOWN
Platform: UNKNOWN
Classifier: Development Status :: 4 - Beta
Classifier: License :: OSI Approved :: MIT License
Classifier: Programming Language :: Python
